cakework/__init__.py
cakework/cakework.py
cakework/cakework_pb2.py
cakework/cakework_pb2.pyi
cakework/cakework_pb2_grpc.py
cakework/client.py
cakework/exceptions.py
cakework/frontend_pb2.py
cakework/frontend_pb2.pyi
cakework/frontend_pb2_grpc.py
cakework/requirements_cakework.txt
cakework/task_server.py
cakework-0.0.61.dist-info/METADATA
cakework-0.0.61.dist-info/WHEEL
cakework-0.0.61.dist-info/RECORD
