Metadata-Version: 2.1
Name: cakework
Version: 0.0.61
Summary: Cakework Python SDK
Project-URL: Homepage, https://github.com/usecakework/cakework
Project-URL: Bug Tracker, https://github.com/usecakework/cakework/issues
Author-email: Jessie Young <jessie@cakework.com>
Classifier: License :: OSI Approved :: MIT License
Classifier: Operating System :: OS Independent
Classifier: Programming Language :: Python :: 3
Requires-Python: >=3.7
Requires-Dist: grpcio
Requires-Dist: protobuf
Requires-Dist: requests
